sum04007/__init__.py
sum04007-0.0.1.dist-info/METADATA
sum04007-0.0.1.dist-info/WHEEL
sum04007-0.0.1.dist-info/top_level.txt
sum04007-0.0.1.dist-info/RECORD
