Metadata-Version: 2.1
Name: sum04007
Version: 0.0.1
Summary: Addition
Home-page: UNKNOWN
Author: NomanSaeedSoomro
Author-email: nomiahmad90@gmail.com
License: UNKNOWN
Platform: UNKNOWN
Classifier: Programming Language :: Python :: 3
Classifier: License :: OSI Approved :: MIT License
Classifier: Operating System :: OS Independent
